ncs2_device_plugin/__init__.py
ncs2_device_plugin/main.py
ncs2_device_plugin/ncs2.py
ncs2_device_plugin/usb_monitor.py
ncs2_device_plugin-0.1.0.dist-info/LICENSE
ncs2_device_plugin-0.1.0.dist-info/METADATA
ncs2_device_plugin-0.1.0.dist-info/WHEEL
ncs2_device_plugin-0.1.0.dist-info/entry_points.txt
ncs2_device_plugin-0.1.0.dist-info/top_level.txt
ncs2_device_plugin-0.1.0.dist-info/RECORD
