Metadata-Version: 2.1
Name: ncs2-device-plugin
Version: 0.1.0
Summary: Intel NCS2 device plugin for Kubernetes
Home-page: https://github.com/adaptant-labs/ncs2-device-plugin
Author: Adaptant Labs
Author-email: labs@adaptant.io
License: Apache 2.0
Keywords: kubernetes,movidius,ncs2,myriad,myriadx,monitoring
Platform: UNKNOWN
Classifier: Development Status :: 4 - Beta
Classifier: Intended Audience :: Developers
Classifier: Intended Audience :: System Administrators
Classifier: Topic :: System :: Hardware
Classifier: Topic :: System :: Monitoring
Classifier: Programming Language :: Python :: 3
Classifier: Programming Language :: Python :: 3.7
Classifier: Programming Language :: Python :: 3.8
Classifier: License :: OSI Approved :: Apache Software License
Requires-Dist: kubernetes
Requires-Dist: pyudev
Requires-Dist: pyusb
